CurrencyViewer/__init__.py
CurrencyViewer/currency_viewer.py
CurrencyViewer/currencyviewer.py
currency_viewer/__init__.py
currency_viewer/currency_viewer.py
currency_viewer-0.2.1.dist-info/METADATA
currency_viewer-0.2.1.dist-info/RECORD
currency_viewer-0.2.1.dist-info/WHEEL
currency_viewer-0.2.1.dist-info/top_level.txt
