Metadata-Version: 2.1
Name: currency-viewer
Version: 0.2.1
Summary: Currency Viewer is a Kraken exchange framework
Home-page: https://github.com/smechaab/CurrencyViewer
Author: Semy Mechaab
Author-email: s.mechaab@protonmail.com
Maintainer: Semy Mechaab
Maintainer-email: s.mechaab@protonmail.com
License: GPL V3
Keywords: cryptocurrencies kraken wallet bitcoin api converter currency exchange csv-files module package
Platform: ALL
Requires-Dist: krakenex (>=2.1.0)
